bullpenfi/__init__.cpython-311.pyc
bullpenfi/__init__.py
bullpenfi/auth.cpython-311.pyc
bullpenfi/auth.py
bullpenfi/module1.cpython-311.pyc
bullpenfi/module1.py
bullpenfi/ping.cpython-311.pyc
bullpenfi/ping.py
bullpenfi/services/__init__.py
bullpenfi/services/google_sheet.py
bullpenfi/services/semantic_kernel.py
bullpenfi/services/telegram.py
bullpenfi/services/__pycache__/__init__.cpython-311.pyc
bullpenfi/services/__pycache__/google_sheet.cpython-311.pyc
bullpenfi/services/__pycache__/semantic_kernel.cpython-311.pyc
bullpenfi/services/__pycache__/telegram.cpython-311.pyc
tests/__init__.py
tests/test_module1.py
bullpenfi-0.1.11.dist-info/LICENSE.txt
bullpenfi-0.1.11.dist-info/METADATA
bullpenfi-0.1.11.dist-info/WHEEL
bullpenfi-0.1.11.dist-info/top_level.txt
bullpenfi-0.1.11.dist-info/RECORD
