Metadata-Version: 2.1
Name: bullpenfi
Version: 0.1.11
Summary: A description of your package
Home-page: https://github.com/yourusername/bullpenfi
Author: Dev at Bullpen Labs
Author-email: dev@bullpen.fi
Classifier: Programming Language :: Python :: 3
Classifier: License :: Other/Proprietary License
Classifier: Operating System :: OS Independent
Requires-Python: >=3.6
License-File: LICENSE.txt
Requires-Dist: requests
Requires-Dist: numpy
